bm/recursive_functions/__init__.py
bm/recursive_functions/examples.py
bm/recursive_functions/py.typed
bm/recursive_functions/cli/__init__.py
bm/recursive_functions/cli/ackermann.py
bm/recursive_functions/cli/py.typed
bm_recursive_functions-0.6.1.dist-info/entry_points.txt
bm_recursive_functions-0.6.1.dist-info/licenses/LICENSE
bm_recursive_functions-0.6.1.dist-info/WHEEL
bm_recursive_functions-0.6.1.dist-info/METADATA
bm_recursive_functions-0.6.1.dist-info/RECORD
