Metadata-Version: 2.4
Name: bm.recursive-functions
Version: 0.6.1
Summary: Recursive Functions Package
Keywords: ackermann,fibonacci,recursive,recursive functions
Author-email: "Geoffrey R. Scheller" <geoffrey@scheller.com>
Requires-Python: >=3.12
Classifier: Development Status :: 3 - Alpha
Classifier: Framework :: Pytest
Classifier: Intended Audience :: Education
Classifier: License :: OSI Approved :: Apache Software License
Classifier: Operating System :: OS Independent
Classifier: Programming Language :: Python :: 3.13
Classifier: Typing :: Typed
License-File: LICENSE
Project-URL: Changelog, https://github.com/grscheller/bm-recursive-functions/blob/main/CHANGELOG.md
Project-URL: Documentation, https://grscheller.github.io/bm-docs/recursive-functions/
Project-URL: Homepage, https://github.com/grscheller/bm-docs/blob/main/README.md
Project-URL: Source, https://github.com/grscheller/bm-recursive-functions
